{
    "customers": [
      { "id": 1, "name": "Ahmed Ali" },
      { "id": 2, "name": "Aya Elsayed" },
      { "id": 3, "name": "Mina Adel" },
      { "id": 4, "name": "Sarah Reda" },
      { "id": 5, "name": "Mohamed Elsayed" },
      { "id": 6, "name": "Abdulrahman Magdy" }
    ],
    "transactions": [
      { "id": 1, "customer_id": 1, "date": "2022-01-01", "amount": 1000 },
      { "id": 2, "customer_id": 1, "date": "2022-01-02", "amount": 1850 },
      { "id": 3, "customer_id": 2, "date": "2022-01-01", "amount": 550 },
      { "id": 4, "customer_id": 3, "date": "2022-01-01", "amount": 500 },
      { "id": 5, "customer_id": 2, "date": "2022-01-02", "amount": 1300 },
      { "id": 6, "customer_id": 4, "date": "2022-01-01", "amount": 750 },
      { "id": 7, "customer_id": 3, "date": "2022-01-02", "amount": 1250 },
      { "id": 8, "customer_id": 5, "date": "2022-01-01", "amount": 1500 },
      { "id": 9, "customer_id": 5, "date": "2022-01-02", "amount": 875 },
      { "id": 10, "customer_id": 6, "date": "2023-10-01", "amount": 1490 },
      { "id": 11, "customer_id": 6, "date": "2023-11-06", "amount": 999 },
      { "id": 12, "customer_id": 6, "date": "2023-12-20", "amount": 1600 },
      { "id": 13, "customer_id": 5, "date": "2024-02-06", "amount": 1000 },
      { "id": 14, "customer_id": 6, "date": "2024-04-15", "amount": 1960 },
      { "id": 15, "customer_id": 4, "date": "2024-06-06", "amount": 999 },
      { "id": 16, "customer_id": 1, "date": "2024-07-20", "amount": 1600 },
      { "id": 17, "customer_id": 2, "date": "2024-06-06", "amount": 1000 },
      { "id": 18, "customer_id": 3, "date": "2024-01-15", "amount": 1960 },
      { "id": 18, "customer_id": 1, "date": "2024-01-15", "amount": 1960 }

    ]
  }